MANIFEST.in
README
ez_setup.py
libgearman.c
setup.py
test_client.py
test_client_bg.py
test_worker.py
gearman/__init__.py
gearman/libgearman.py
gearman/release.py
python_libgearman.egg-info/PKG-INFO
python_libgearman.egg-info/SOURCES.txt
python_libgearman.egg-info/dependency_links.txt
python_libgearman.egg-info/top_level.txt