Metadata-Version: 1.0
Name: python-libgearman
Version: 0.13.2
Summary: Python wrapper of libgearman
Home-page: http://launchpad.net/gearman-interface
Author: Monty Taylor
Author-email: mordred@inaugust.com
License: GPL
Platform: linux
Classifier: Development Status :: 2 - Pre-Alpha
Classifier: License :: OSI Approved :: BSD License
Classifier: Operating System :: POSIX :: Linux
Classifier: Programming Language :: C++
Classifier: Programming Language :: Python
Classifier: Topic :: Software Development :: Libraries :: Python Modules
